odoo/addons/attribute_set_mass_edit/README.rst
odoo/addons/attribute_set_mass_edit/__init__.py
odoo/addons/attribute_set_mass_edit/__manifest__.py
odoo/addons/attribute_set_mass_edit/i18n/attribute_set_mass_edit.pot
odoo/addons/attribute_set_mass_edit/models/__init__.py
odoo/addons/attribute_set_mass_edit/models/attribute_attribute.py
odoo/addons/attribute_set_mass_edit/models/attribute_group.py
odoo/addons/attribute_set_mass_edit/models/mass_editing.py
odoo/addons/attribute_set_mass_edit/readme/CONTRIBUTORS.rst
odoo/addons/attribute_set_mass_edit/readme/DESCRIPTION.rst
odoo/addons/attribute_set_mass_edit/readme/USAGE.rst
odoo/addons/attribute_set_mass_edit/static/description/icon.png
odoo/addons/attribute_set_mass_edit/static/description/index.html
odoo/addons/attribute_set_mass_edit/tests/__init__.py
odoo/addons/attribute_set_mass_edit/tests/test_attribute_set_mass_edit.py
odoo/addons/attribute_set_mass_edit/views/attribute_attribute.xml
odoo/addons/attribute_set_mass_edit/wizards/__init__.py
odoo/addons/attribute_set_mass_edit/wizards/mass_editing_wizard.py
odoo12_addon_attribute_set_mass_edit-12.0.2.0.0.99.dev7.dist-info/METADATA
odoo12_addon_attribute_set_mass_edit-12.0.2.0.0.99.dev7.dist-info/WHEEL
odoo12_addon_attribute_set_mass_edit-12.0.2.0.0.99.dev7.dist-info/top_level.txt
odoo12_addon_attribute_set_mass_edit-12.0.2.0.0.99.dev7.dist-info/RECORD
