Metadata-Version: 2.1
Name: odoo12-addon-attribute-set-mass-edit
Version: 12.0.2.0.0.99.dev7
Summary: Attribute Set Mass Edit
Home-page: https://github.com/OCA/odoo-pim
Author: ACSONE SA/NV,Odoo Community Association (OCA)
Author-email: support@odoo-community.org
License: AGPL-3
Platform: UNKNOWN
Classifier: Programming Language :: Python
Classifier: Framework :: Odoo
Classifier: Framework :: Odoo :: 12.0
Classifier: License :: OSI Approved :: GNU Affero General Public License v3
Requires-Python: >=3.5
Requires-Dist: odoo12-addon-attribute-set
Requires-Dist: odoo12-addon-mass-editing
Requires-Dist: odoo <12.1dev,>=12.0a
